invisible_qr_watermark/__init__.py
invisible_qr_watermark/image.py
tests/__init__.py
tests/test_image.py
invisible_qr_watermark-0.0.1.dist-info/LICENSE
invisible_qr_watermark-0.0.1.dist-info/METADATA
invisible_qr_watermark-0.0.1.dist-info/WHEEL
invisible_qr_watermark-0.0.1.dist-info/top_level.txt
invisible_qr_watermark-0.0.1.dist-info/RECORD
