Metadata-Version: 2.1
Name: invisible-qr-watermark
Version: 0.0.1
Summary: Encode and decode Image wih text in a form of invisible QR code
Home-page: https://github.com/SerhiiStets/invisible_qr_watermark
Author: Serhii Stets
Author-email: stets.serhii@gmail.com
Classifier: Programming Language :: Python :: 3
Classifier: License :: OSI Approved :: MIT License
Classifier: Operating System :: OS Independent
Requires-Python: >=3.6
License-File: LICENSE
